hoocron_plugin/redis/__init__.py
hoocron_plugin_redis-0.0.4.dist-info/LICENSE
hoocron_plugin_redis-0.0.4.dist-info/METADATA
hoocron_plugin_redis-0.0.4.dist-info/WHEEL
hoocron_plugin_redis-0.0.4.dist-info/top_level.txt
hoocron_plugin_redis-0.0.4.dist-info/RECORD
