Metadata-Version: 2.1
Name: hoocron-plugin-redis
Version: 0.0.4
Summary: Redis plugin for Hoocron
Home-page: https://github.com/yaroslaff/hoocron-plugin-redis
Author: Yaroslav Polyakov
Author-email: yaroslaff@gmail.com
License: MIT
Platform: UNKNOWN
Classifier: Development Status :: 3 - Alpha
Classifier: Intended Audience :: Developers
Classifier: License :: OSI Approved :: MIT License
Classifier: Programming Language :: Python :: 3.4
Requires-Python: >=3
Requires-Dist: hoocron
Requires-Dist: redis
